boomerang/__init__.py
boomerang/client.py
boomerang_client-0.11.dist-info/WHEEL
boomerang_client-0.11.dist-info/DESCRIPTION.rst
boomerang_client-0.11.dist-info/top_level.txt
boomerang_client-0.11.dist-info/METADATA
boomerang_client-0.11.dist-info/metadata.json
boomerang_client-0.11.dist-info/RECORD
