Metadata-Version: 2.0
Name: boomerang-client
Version: 0.11
Summary: Boomerang.io Python API client
Home-page: https://github.com/olalidmark/boomerang-client
Author: fantomen
Author-email: olalidmark@gmail.com
License: MIT
Keywords: boomerang,boomerang.io,api,rest
Platform: UNKNOWN
Classifier: Development Status :: 4 - Beta
Classifier: Intended Audience :: Developers
Classifier: License :: OSI Approved :: MIT License
Classifier: Programming Language :: Python :: 2
Classifier: Programming Language :: Python :: 2.7
Requires-Dist: requests
